windows_capture-1.4.4.dist-info/METADATA
windows_capture-1.4.4.dist-info/WHEEL
windows_capture-1.4.4.dist-info/licenses/LICENCE
windows_capture/__init__.py
windows_capture/windows_capture.pyd
windows_capture-1.4.4.dist-info/RECORD
