Metadata-Version: 2.4
Name: windows-capture
Version: 1.4.4
Classifier: Development Status :: 5 - Production/Stable
Classifier: Environment :: GPU
Classifier: Intended Audience :: Developers
Classifier: License :: OSI Approved :: MIT License
Classifier: Programming Language :: Rust
Classifier: Programming Language :: Python
Classifier: Topic :: Multimedia
Classifier: Topic :: Multimedia :: Graphics :: Capture
Classifier: Topic :: Multimedia :: Graphics :: Capture :: Screen Capture
Classifier: Topic :: Multimedia :: Video :: Capture
Requires-Dist: numpy
Requires-Dist: opencv-python
License-File: LICENCE
Summary: Fastest Windows Screen Capture Library For Python 🔥
Keywords: screen,capture,screenshot,graphics,windows
Author: NiiightmareXD
License: MIT
Requires-Python: >=3.9
Project-URL: Source Code, https://github.com/NiiightmareXD/windows-capture/tree/main/windows-capture-python
